configglue/__init__.py
configglue/_compat.py
configglue/glue.py
configglue/parser.py
configglue/schema.py
configglue/app/__init__.py
configglue/app/base.py
configglue/app/plugin.py
configglue/contrib/__init__.py
configglue/contrib/schema/__init__.py
configglue/contrib/schema/devserver.py
configglue/contrib/schema/django_jenkins.py
configglue/contrib/schema/django_openid_auth.py
configglue/contrib/schema/nexus.py
configglue/contrib/schema/preflight.py
configglue/contrib/schema/pystatsd.py
configglue/contrib/schema/raven.py
configglue/contrib/schema/saml2idp.py
configglue/inischema/__init__.py
configglue/inischema/attributed.py
configglue/inischema/glue.py
configglue/inischema/parsers.py
configglue/inischema/typed.py
configglue/tests/__init__.py
configglue/tests/test_contrib_schema.py
configglue/tests/test_parser.py
configglue/tests/test_schema.py
configglue/tests/test_schemaconfig.py
configglue/tests/app/__init__.py
configglue/tests/app/test_base.py
configglue/tests/app/test_plugin.py
configglue/tests/inischema/__init__.py
configglue/tests/inischema/test_attributed.py
configglue/tests/inischema/test_glue.py
configglue/tests/inischema/test_glue2glue.py
configglue/tests/inischema/test_parsers.py
configglue/tests/inischema/test_typed.py
configglue-1.1.3.dist-info/LICENSE
configglue-1.1.3.dist-info/METADATA
configglue-1.1.3.dist-info/WHEEL
configglue-1.1.3.dist-info/dependency_links.txt
configglue-1.1.3.dist-info/top_level.txt
configglue-1.1.3.dist-info/zip-safe
configglue-1.1.3.dist-info/RECORD
