Metadata-Version: 2.1
Name: configglue
Version: 1.1.3
Summary: Glue to stick OptionParser and ConfigParser together
Home-page: https://launchpad.net/configglue
Author: John R. Lenton, Ricardo Kirkner
Author-email: john.lenton@canonical.com, ricardo.kirkner@canonical.com
License: BSD License
Platform: UNKNOWN
Classifier: License :: OSI Approved :: BSD License
Classifier: Topic :: Software Development :: Libraries :: Python Modules
Classifier: Programming Language :: Python
Classifier: Programming Language :: Python :: 2
Classifier: Programming Language :: Python :: 2.6
Classifier: Programming Language :: Python :: 2.7
Classifier: Programming Language :: Python :: 3
Classifier: Programming Language :: Python :: 3.2
Classifier: Programming Language :: Python :: 3.3
Requires-Dist: pyxdg
